{"entities":[],"tiles":["{\"alternative_tile\":\"0\",\"atlas_coords\":\"Vector2i(26, 4)\",\"coordinate\":\"Vector2i(-112, 16)\",\"source_id\":\"0\"}","{\"alternative_tile\":\"0\",\"atlas_coords\":\"Vector2i(26, 10)\",\"coordinate\":\"Vector2i(-112, 17)\",\"source_id\":\"0\"}","{\"alternative_tile\":\"0\",\"atlas_coords\":\"Vector2i(26, 10)\",\"coordinate\":\"Vector2i(-112, 18)\",\"source_id\":\"0\"}","{\"alternative_tile\":\"0\",\"atlas_coords\":\"Vector2i(26, 4)\",\"coordinate\":\"Vector2i(-112, 19)\",\"source_id\":\"0\"}","{\"alternative_tile\":\"0\",\"atlas_coords\":\"Vector2i(26, 4)\",\"coordinate\":\"Vector2i(-112, 20)\",\"source_id\":\"0\"}","{\"alternative_tile\":\"0\",\"atlas_coords\":\"Vector2i(26, 4)\",\"coordinate\":\"Vector2i(-112, 21)\",\"source_id\":\"0\"}","{\"alternative_tile\":\"0\",\"atlas_coords\":\"Vector2i(26, 4)\",\"coordinate\":\"Vector2i(-112, 22)\",\"source_id\":\"0\"}","{\"alternative_tile\":\"0\",\"atlas_coords\":\"Vector2i(26, 10)\",\"coordinate\":\"Vector2i(-112, 23)\",\"source_id\":\"0\"}","{\"alternative_tile\":\"0\",\"atlas_coords\":\"Vector2i(26, 4)\",\"coordinate\":\"Vector2i(-111, 16)\",\"source_id\":\"0\"}","{\"alternative_tile\":\"0\",\"atlas_coords\":\"Vector2i(26, 10)\",\"coordinate\":\"Vector2i(-111, 17)\",\"source_id\":\"0\"}","{\"alternative_tile\":\"0\",\"atlas_coords\":\"Vector2i(26, 10)\",\"coordinate\":\"Vector2i(-111, 18)\",\"source_id\":\"0\"}","{\"alternative_tile\":\"0\",\"atlas_coords\":\"Vector2i(26, 4)\",\"coordinate\":\"Vector2i(-111, 19)\",\"source_id\":\"0\"}","{\"alternative_tile\":\"0\",\"atlas_coords\":\"Vector2i(26, 4)\",\"coordinate\":\"Vector2i(-111, 20)\",\"source_id\":\"0\"}","{\"alternative_tile\":\"0\",\"atlas_coords\":\"Vector2i(26, 10)\",\"coordinate\":\"Vector2i(-111, 21)\",\"source_id\":\"0\"}","{\"alternative_tile\":\"0\",\"atlas_coords\":\"Vector2i(26, 10)\",\"coordinate\":\"Vector2i(-111, 22)\",\"source_id\":\"0\"}","{\"alternative_tile\":\"0\",\"atlas_coords\":\"Vector2i(26, 10)\",\"coordinate\":\"Vector2i(-111, 23)\",\"source_id\":\"0\"}","{\"alternative_tile\":\"0\",\"atlas_coords\":\"Vector2i(26, 4)\",\"coordinate\":\"Vector2i(-110, 16)\",\"source_id\":\"0\"}","{\"alternative_tile\":\"0\",\"atlas_coords\":\"Vector2i(26, 4)\",\"coordinate\":\"Vector2i(-110, 17)\",\"source_id\":\"0\"}","{\"alternative_tile\":\"0\",\"atlas_coords\":\"Vector2i(26, 4)\",\"coordinate\":\"Vector2i(-110, 18)\",\"source_id\":\"0\"}","{\"alternative_tile\":\"0\",\"atlas_coords\":\"Vector2i(26, 10)\",\"coordinate\":\"Vector2i(-110, 19)\",\"source_id\":\"0\"}","{\"alternative_tile\":\"0\",\"atlas_coords\":\"Vector2i(26, 10)\",\"coordinate\":\"Vector2i(-110, 20)\",\"source_id\":\"0\"}","{\"alternative_tile\":\"0\",\"atlas_coords\":\"Vector2i(26, 10)\",\"coordinate\":\"Vector2i(-110, 21)\",\"source_id\":\"0\"}","{\"alternative_tile\":\"0\",\"atlas_coords\":\"Vector2i(26, 4)\",\"coordinate\":\"Vector2i(-110, 22)\",\"source_id\":\"0\"}","{\"alternative_tile\":\"0\",\"atlas_coords\":\"Vector2i(26, 4)\",\"coordinate\":\"Vector2i(-110, 23)\",\"source_id\":\"0\"}","{\"alternative_tile\":\"0\",\"atlas_coords\":\"Vector2i(26, 4)\",\"coordinate\":\"Vector2i(-109, 16)\",\"source_id\":\"0\"}","{\"alternative_tile\":\"0\",\"atlas_coords\":\"Vector2i(26, 4)\",\"coordinate\":\"Vector2i(-109, 17)\",\"source_id\":\"0\"}","{\"alternative_tile\":\"0\",\"atlas_coords\":\"Vector2i(26, 10)\",\"coordinate\":\"Vector2i(-109, 18)\",\"source_id\":\"0\"}","{\"alternative_tile\":\"0\",\"atlas_coords\":\"Vector2i(26, 10)\",\"coordinate\":\"Vector2i(-109, 19)\",\"source_id\":\"0\"}","{\"alternative_tile\":\"0\",\"atlas_coords\":\"Vector2i(26, 10)\",\"coordinate\":\"Vector2i(-109, 20)\",\"source_id\":\"0\"}","{\"alternative_tile\":\"0\",\"atlas_coords\":\"Vector2i(26, 10)\",\"coordinate\":\"Vector2i(-109, 21)\",\"source_id\":\"0\"}","{\"alternative_tile\":\"0\",\"atlas_coords\":\"Vector2i(26, 10)\",\"coordinate\":\"Vector2i(-109, 22)\",\"source_id\":\"0\"}","{\"alternative_tile\":\"0\",\"atlas_coords\":\"Vector2i(26, 4)\",\"coordinate\":\"Vector2i(-109, 23)\",\"source_id\":\"0\"}","{\"alternative_tile\":\"0\",\"atlas_coords\":\"Vector2i(26, 10)\",\"coordinate\":\"Vector2i(-108, 16)\",\"source_id\":\"0\"}","{\"alternative_tile\":\"0\",\"atlas_coords\":\"Vector2i(26, 4)\",\"coordinate\":\"Vector2i(-108, 17)\",\"source_id\":\"0\"}","{\"alternative_tile\":\"0\",\"atlas_coords\":\"Vector2i(26, 10)\",\"coordinate\":\"Vector2i(-108, 18)\",\"source_id\":\"0\"}","{\"alternative_tile\":\"0\",\"atlas_coords\":\"Vector2i(26, 10)\",\"coordinate\":\"Vector2i(-108, 19)\",\"source_id\":\"0\"}","{\"alternative_tile\":\"0\",\"atlas_coords\":\"Vector2i(26, 4)\",\"coordinate\":\"Vector2i(-108, 20)\",\"source_id\":\"0\"}","{\"alternative_tile\":\"0\",\"atlas_coords\":\"Vector2i(26, 4)\",\"coordinate\":\"Vector2i(-108, 21)\",\"source_id\":\"0\"}","{\"alternative_tile\":\"0\",\"atlas_coords\":\"Vector2i(26, 4)\",\"coordinate\":\"Vector2i(-108, 22)\",\"source_id\":\"0\"}","{\"alternative_tile\":\"0\",\"atlas_coords\":\"Vector2i(26, 10)\",\"coordinate\":\"Vector2i(-108, 23)\",\"source_id\":\"0\"}","{\"alternative_tile\":\"0\",\"atlas_coords\":\"Vector2i(26, 10)\",\"coordinate\":\"Vector2i(-107, 16)\",\"source_id\":\"0\"}","{\"alternative_tile\":\"0\",\"atlas_coords\":\"Vector2i(26, 10)\",\"coordinate\":\"Vector2i(-107, 17)\",\"source_id\":\"0\"}","{\"alternative_tile\":\"0\",\"atlas_coords\":\"Vector2i(26, 4)\",\"coordinate\":\"Vector2i(-107, 18)\",\"source_id\":\"0\"}","{\"alternative_tile\":\"0\",\"atlas_coords\":\"Vector2i(26, 4)\",\"coordinate\":\"Vector2i(-107, 19)\",\"source_id\":\"0\"}","{\"alternative_tile\":\"0\",\"atlas_coords\":\"Vector2i(26, 10)\",\"coordinate\":\"Vector2i(-107, 20)\",\"source_id\":\"0\"}","{\"alternative_tile\":\"0\",\"atlas_coords\":\"Vector2i(26, 4)\",\"coordinate\":\"Vector2i(-107, 21)\",\"source_id\":\"0\"}","{\"alternative_tile\":\"0\",\"atlas_coords\":\"Vector2i(26, 10)\",\"coordinate\":\"Vector2i(-107, 22)\",\"source_id\":\"0\"}","{\"alternative_tile\":\"0\",\"atlas_coords\":\"Vector2i(26, 4)\",\"coordinate\":\"Vector2i(-107, 23)\",\"source_id\":\"0\"}","{\"alternative_tile\":\"0\",\"atlas_coords\":\"Vector2i(26, 10)\",\"coordinate\":\"Vector2i(-106, 16)\",\"source_id\":\"0\"}","{\"alternative_tile\":\"0\",\"atlas_coords\":\"Vector2i(26, 4)\",\"coordinate\":\"Vector2i(-106, 17)\",\"source_id\":\"0\"}","{\"alternative_tile\":\"0\",\"atlas_coords\":\"Vector2i(26, 4)\",\"coordinate\":\"Vector2i(-106, 18)\",\"source_id\":\"0\"}","{\"alternative_tile\":\"0\",\"atlas_coords\":\"Vector2i(26, 10)\",\"coordinate\":\"Vector2i(-106, 19)\",\"source_id\":\"0\"}","{\"alternative_tile\":\"0\",\"atlas_coords\":\"Vector2i(26, 10)\",\"coordinate\":\"Vector2i(-106, 20)\",\"source_id\":\"0\"}","{\"alternative_tile\":\"0\",\"atlas_coords\":\"Vector2i(26, 10)\",\"coordinate\":\"Vector2i(-106, 21)\",\"source_id\":\"0\"}","{\"alternative_tile\":\"0\",\"atlas_coords\":\"Vector2i(26, 10)\",\"coordinate\":\"Vector2i(-106, 22)\",\"source_id\":\"0\"}","{\"alternative_tile\":\"0\",\"atlas_coords\":\"Vector2i(26, 4)\",\"coordinate\":\"Vector2i(-106, 23)\",\"source_id\":\"0\"}","{\"alternative_tile\":\"0\",\"atlas_coords\":\"Vector2i(26, 4)\",\"coordinate\":\"Vector2i(-105, 16)\",\"source_id\":\"0\"}","{\"alternative_tile\":\"0\",\"atlas_coords\":\"Vector2i(26, 4)\",\"coordinate\":\"Vector2i(-105, 17)\",\"source_id\":\"0\"}","{\"alternative_tile\":\"0\",\"atlas_coords\":\"Vector2i(26, 4)\",\"coordinate\":\"Vector2i(-105, 18)\",\"source_id\":\"0\"}","{\"alternative_tile\":\"0\",\"atlas_coords\":\"Vector2i(26, 10)\",\"coordinate\":\"Vector2i(-105, 19)\",\"source_id\":\"0\"}","{\"alternative_tile\":\"0\",\"atlas_coords\":\"Vector2i(26, 4)\",\"coordinate\":\"Vector2i(-105, 20)\",\"source_id\":\"0\"}","{\"alternative_tile\":\"0\",\"atlas_coords\":\"Vector2i(26, 10)\",\"coordinate\":\"Vector2i(-105, 21)\",\"source_id\":\"0\"}","{\"alternative_tile\":\"0\",\"atlas_coords\":\"Vector2i(26, 10)\",\"coordinate\":\"Vector2i(-105, 22)\",\"source_id\":\"0\"}","{\"alternative_tile\":\"0\",\"atlas_coords\":\"Vector2i(26, 10)\",\"coordinate\":\"Vector2i(-105, 23)\",\"source_id\":\"0\"}"]}