{"entities":[],"tiles":["{\"alternative_tile\":\"0\",\"atlas_coords\":\"Vector2i(26, 4)\",\"coordinate\":\"Vector2i(-64, -104)\",\"source_id\":\"0\"}","{\"alternative_tile\":\"0\",\"atlas_coords\":\"Vector2i(26, 4)\",\"coordinate\":\"Vector2i(-64, -103)\",\"source_id\":\"0\"}","{\"alternative_tile\":\"0\",\"atlas_coords\":\"Vector2i(26, 4)\",\"coordinate\":\"Vector2i(-64, -102)\",\"source_id\":\"0\"}","{\"alternative_tile\":\"0\",\"atlas_coords\":\"Vector2i(26, 5)\",\"coordinate\":\"Vector2i(-64, -101)\",\"source_id\":\"0\"}","{\"alternative_tile\":\"0\",\"atlas_coords\":\"Vector2i(37, 11)\",\"coordinate\":\"Vector2i(-64, -100)\",\"source_id\":\"0\"}","{\"alternative_tile\":\"0\",\"atlas_coords\":\"Vector2i(37, 11)\",\"coordinate\":\"Vector2i(-64, -99)\",\"source_id\":\"0\"}","{\"alternative_tile\":\"0\",\"atlas_coords\":\"Vector2i(3, 3)\",\"coordinate\":\"Vector2i(-64, -98)\",\"source_id\":\"0\"}","{\"alternative_tile\":\"0\",\"atlas_coords\":\"Vector2i(1, 1)\",\"coordinate\":\"Vector2i(-64, -97)\",\"source_id\":\"0\"}","{\"alternative_tile\":\"0\",\"atlas_coords\":\"Vector2i(26, 4)\",\"coordinate\":\"Vector2i(-63, -104)\",\"source_id\":\"0\"}","{\"alternative_tile\":\"0\",\"atlas_coords\":\"Vector2i(26, 4)\",\"coordinate\":\"Vector2i(-63, -103)\",\"source_id\":\"0\"}","{\"alternative_tile\":\"0\",\"atlas_coords\":\"Vector2i(26, 10)\",\"coordinate\":\"Vector2i(-63, -102)\",\"source_id\":\"0\"}","{\"alternative_tile\":\"0\",\"atlas_coords\":\"Vector2i(26, 5)\",\"coordinate\":\"Vector2i(-63, -101)\",\"source_id\":\"0\"}","{\"alternative_tile\":\"0\",\"atlas_coords\":\"Vector2i(37, 11)\",\"coordinate\":\"Vector2i(-63, -100)\",\"source_id\":\"0\"}","{\"alternative_tile\":\"0\",\"atlas_coords\":\"Vector2i(37, 11)\",\"coordinate\":\"Vector2i(-63, -99)\",\"source_id\":\"0\"}","{\"alternative_tile\":\"0\",\"atlas_coords\":\"Vector2i(4, 3)\",\"coordinate\":\"Vector2i(-63, -98)\",\"source_id\":\"0\"}","{\"alternative_tile\":\"0\",\"atlas_coords\":\"Vector2i(4, 4)\",\"coordinate\":\"Vector2i(-63, -97)\",\"source_id\":\"0\"}","{\"alternative_tile\":\"0\",\"atlas_coords\":\"Vector2i(26, 10)\",\"coordinate\":\"Vector2i(-62, -104)\",\"source_id\":\"0\"}","{\"alternative_tile\":\"0\",\"atlas_coords\":\"Vector2i(26, 4)\",\"coordinate\":\"Vector2i(-62, -103)\",\"source_id\":\"0\"}","{\"alternative_tile\":\"0\",\"atlas_coords\":\"Vector2i(26, 10)\",\"coordinate\":\"Vector2i(-62, -102)\",\"source_id\":\"0\"}","{\"alternative_tile\":\"0\",\"atlas_coords\":\"Vector2i(26, 5)\",\"coordinate\":\"Vector2i(-62, -101)\",\"source_id\":\"0\"}","{\"alternative_tile\":\"0\",\"atlas_coords\":\"Vector2i(37, 11)\",\"coordinate\":\"Vector2i(-62, -100)\",\"source_id\":\"0\"}","{\"alternative_tile\":\"0\",\"atlas_coords\":\"Vector2i(37, 11)\",\"coordinate\":\"Vector2i(-62, -99)\",\"source_id\":\"0\"}","{\"alternative_tile\":\"0\",\"atlas_coords\":\"Vector2i(37, 11)\",\"coordinate\":\"Vector2i(-62, -98)\",\"source_id\":\"0\"}","{\"alternative_tile\":\"0\",\"atlas_coords\":\"Vector2i(37, 11)\",\"coordinate\":\"Vector2i(-62, -97)\",\"source_id\":\"0\"}","{\"alternative_tile\":\"0\",\"atlas_coords\":\"Vector2i(26, 10)\",\"coordinate\":\"Vector2i(-61, -104)\",\"source_id\":\"0\"}","{\"alternative_tile\":\"0\",\"atlas_coords\":\"Vector2i(26, 4)\",\"coordinate\":\"Vector2i(-61, -103)\",\"source_id\":\"0\"}","{\"alternative_tile\":\"0\",\"atlas_coords\":\"Vector2i(26, 4)\",\"coordinate\":\"Vector2i(-61, -102)\",\"source_id\":\"0\"}","{\"alternative_tile\":\"0\",\"atlas_coords\":\"Vector2i(26, 5)\",\"coordinate\":\"Vector2i(-61, -101)\",\"source_id\":\"0\"}","{\"alternative_tile\":\"0\",\"atlas_coords\":\"Vector2i(37, 11)\",\"coordinate\":\"Vector2i(-61, -100)\",\"source_id\":\"0\"}","{\"alternative_tile\":\"0\",\"atlas_coords\":\"Vector2i(37, 11)\",\"coordinate\":\"Vector2i(-61, -99)\",\"source_id\":\"0\"}","{\"alternative_tile\":\"0\",\"atlas_coords\":\"Vector2i(37, 11)\",\"coordinate\":\"Vector2i(-61, -98)\",\"source_id\":\"0\"}","{\"alternative_tile\":\"0\",\"atlas_coords\":\"Vector2i(37, 11)\",\"coordinate\":\"Vector2i(-61, -97)\",\"source_id\":\"0\"}","{\"alternative_tile\":\"0\",\"atlas_coords\":\"Vector2i(26, 4)\",\"coordinate\":\"Vector2i(-60, -104)\",\"source_id\":\"0\"}","{\"alternative_tile\":\"0\",\"atlas_coords\":\"Vector2i(26, 10)\",\"coordinate\":\"Vector2i(-60, -103)\",\"source_id\":\"0\"}","{\"alternative_tile\":\"0\",\"atlas_coords\":\"Vector2i(26, 10)\",\"coordinate\":\"Vector2i(-60, -102)\",\"source_id\":\"0\"}","{\"alternative_tile\":\"0\",\"atlas_coords\":\"Vector2i(26, 5)\",\"coordinate\":\"Vector2i(-60, -101)\",\"source_id\":\"0\"}","{\"alternative_tile\":\"0\",\"atlas_coords\":\"Vector2i(37, 11)\",\"coordinate\":\"Vector2i(-60, -100)\",\"source_id\":\"0\"}","{\"alternative_tile\":\"0\",\"atlas_coords\":\"Vector2i(37, 11)\",\"coordinate\":\"Vector2i(-60, -99)\",\"source_id\":\"0\"}","{\"alternative_tile\":\"0\",\"atlas_coords\":\"Vector2i(37, 11)\",\"coordinate\":\"Vector2i(-60, -98)\",\"source_id\":\"0\"}","{\"alternative_tile\":\"0\",\"atlas_coords\":\"Vector2i(37, 11)\",\"coordinate\":\"Vector2i(-60, -97)\",\"source_id\":\"0\"}","{\"alternative_tile\":\"0\",\"atlas_coords\":\"Vector2i(26, 4)\",\"coordinate\":\"Vector2i(-59, -104)\",\"source_id\":\"0\"}","{\"alternative_tile\":\"0\",\"atlas_coords\":\"Vector2i(26, 10)\",\"coordinate\":\"Vector2i(-59, -103)\",\"source_id\":\"0\"}","{\"alternative_tile\":\"0\",\"atlas_coords\":\"Vector2i(26, 10)\",\"coordinate\":\"Vector2i(-59, -102)\",\"source_id\":\"0\"}","{\"alternative_tile\":\"0\",\"atlas_coords\":\"Vector2i(26, 5)\",\"coordinate\":\"Vector2i(-59, -101)\",\"source_id\":\"0\"}","{\"alternative_tile\":\"0\",\"atlas_coords\":\"Vector2i(37, 11)\",\"coordinate\":\"Vector2i(-59, -100)\",\"source_id\":\"0\"}","{\"alternative_tile\":\"0\",\"atlas_coords\":\"Vector2i(37, 11)\",\"coordinate\":\"Vector2i(-59, -99)\",\"source_id\":\"0\"}","{\"alternative_tile\":\"0\",\"atlas_coords\":\"Vector2i(37, 11)\",\"coordinate\":\"Vector2i(-59, -98)\",\"source_id\":\"0\"}","{\"alternative_tile\":\"0\",\"atlas_coords\":\"Vector2i(37, 11)\",\"coordinate\":\"Vector2i(-59, -97)\",\"source_id\":\"0\"}","{\"alternative_tile\":\"0\",\"atlas_coords\":\"Vector2i(26, 10)\",\"coordinate\":\"Vector2i(-58, -104)\",\"source_id\":\"0\"}","{\"alternative_tile\":\"0\",\"atlas_coords\":\"Vector2i(26, 10)\",\"coordinate\":\"Vector2i(-58, -103)\",\"source_id\":\"0\"}","{\"alternative_tile\":\"0\",\"atlas_coords\":\"Vector2i(26, 10)\",\"coordinate\":\"Vector2i(-58, -102)\",\"source_id\":\"0\"}","{\"alternative_tile\":\"0\",\"atlas_coords\":\"Vector2i(26, 5)\",\"coordinate\":\"Vector2i(-58, -101)\",\"source_id\":\"0\"}","{\"alternative_tile\":\"0\",\"atlas_coords\":\"Vector2i(2, 3)\",\"coordinate\":\"Vector2i(-58, -100)\",\"source_id\":\"0\"}","{\"alternative_tile\":\"0\",\"atlas_coords\":\"Vector2i(2, 5)\",\"coordinate\":\"Vector2i(-58, -99)\",\"source_id\":\"0\"}","{\"alternative_tile\":\"0\",\"atlas_coords\":\"Vector2i(37, 11)\",\"coordinate\":\"Vector2i(-58, -98)\",\"source_id\":\"0\"}","{\"alternative_tile\":\"0\",\"atlas_coords\":\"Vector2i(37, 11)\",\"coordinate\":\"Vector2i(-58, -97)\",\"source_id\":\"0\"}","{\"alternative_tile\":\"0\",\"atlas_coords\":\"Vector2i(26, 10)\",\"coordinate\":\"Vector2i(-57, -104)\",\"source_id\":\"0\"}","{\"alternative_tile\":\"0\",\"atlas_coords\":\"Vector2i(26, 4)\",\"coordinate\":\"Vector2i(-57, -103)\",\"source_id\":\"0\"}","{\"alternative_tile\":\"0\",\"atlas_coords\":\"Vector2i(26, 4)\",\"coordinate\":\"Vector2i(-57, -102)\",\"source_id\":\"0\"}","{\"alternative_tile\":\"0\",\"atlas_coords\":\"Vector2i(26, 5)\",\"coordinate\":\"Vector2i(-57, -101)\",\"source_id\":\"0\"}","{\"alternative_tile\":\"0\",\"atlas_coords\":\"Vector2i(3, 3)\",\"coordinate\":\"Vector2i(-57, -100)\",\"source_id\":\"0\"}","{\"alternative_tile\":\"0\",\"atlas_coords\":\"Vector2i(3, 5)\",\"coordinate\":\"Vector2i(-57, -99)\",\"source_id\":\"0\"}","{\"alternative_tile\":\"0\",\"atlas_coords\":\"Vector2i(37, 11)\",\"coordinate\":\"Vector2i(-57, -98)\",\"source_id\":\"0\"}","{\"alternative_tile\":\"0\",\"atlas_coords\":\"Vector2i(37, 11)\",\"coordinate\":\"Vector2i(-57, -97)\",\"source_id\":\"0\"}"]}