{"entities":["{\"packed_scene\":\"res://Scenes/tree.tscn\",\"persistant_data\":\"Array[Resource(\\\"res://Tools/World/Load and deload/persistantData.gd\\\")]([Object(Resource,\\\"resource_local_to_scene\\\":false,\\\"resource_name\\\":\\\"\\\",\\\"script\\\":Resource(\\\"res://Tools/World/Load and deload/persistantData.gd\\\"),\\\"node_path\\\":\\\"DamageReceiver\\\",\\\"property\\\":\\\"_amount\\\",\\\"value\\\":100.0)\\n])\",\"position\":\"Vector2(-397, 172)\"}"],"tiles":["{\"alternative_tile\":\"-1\",\"atlas_coords\":\"Vector2i(-1, -1)\",\"coordinate\":\"Vector2i(-56, 16)\",\"source_id\":\"-1\"}","{\"alternative_tile\":\"-1\",\"atlas_coords\":\"Vector2i(-1, -1)\",\"coordinate\":\"Vector2i(-56, 17)\",\"source_id\":\"-1\"}","{\"alternative_tile\":\"-1\",\"atlas_coords\":\"Vector2i(-1, -1)\",\"coordinate\":\"Vector2i(-56, 18)\",\"source_id\":\"-1\"}","{\"alternative_tile\":\"-1\",\"atlas_coords\":\"Vector2i(-1, -1)\",\"coordinate\":\"Vector2i(-56, 19)\",\"source_id\":\"-1\"}","{\"alternative_tile\":\"-1\",\"atlas_coords\":\"Vector2i(-1, -1)\",\"coordinate\":\"Vector2i(-56, 20)\",\"source_id\":\"-1\"}","{\"alternative_tile\":\"-1\",\"atlas_coords\":\"Vector2i(-1, -1)\",\"coordinate\":\"Vector2i(-56, 21)\",\"source_id\":\"-1\"}","{\"alternative_tile\":\"-1\",\"atlas_coords\":\"Vector2i(-1, -1)\",\"coordinate\":\"Vector2i(-56, 22)\",\"source_id\":\"-1\"}","{\"alternative_tile\":\"-1\",\"atlas_coords\":\"Vector2i(-1, -1)\",\"coordinate\":\"Vector2i(-56, 23)\",\"source_id\":\"-1\"}","{\"alternative_tile\":\"-1\",\"atlas_coords\":\"Vector2i(-1, -1)\",\"coordinate\":\"Vector2i(-55, 16)\",\"source_id\":\"-1\"}","{\"alternative_tile\":\"-1\",\"atlas_coords\":\"Vector2i(-1, -1)\",\"coordinate\":\"Vector2i(-55, 17)\",\"source_id\":\"-1\"}","{\"alternative_tile\":\"-1\",\"atlas_coords\":\"Vector2i(-1, -1)\",\"coordinate\":\"Vector2i(-55, 18)\",\"source_id\":\"-1\"}","{\"alternative_tile\":\"-1\",\"atlas_coords\":\"Vector2i(-1, -1)\",\"coordinate\":\"Vector2i(-55, 19)\",\"source_id\":\"-1\"}","{\"alternative_tile\":\"-1\",\"atlas_coords\":\"Vector2i(-1, -1)\",\"coordinate\":\"Vector2i(-55, 20)\",\"source_id\":\"-1\"}","{\"alternative_tile\":\"-1\",\"atlas_coords\":\"Vector2i(-1, -1)\",\"coordinate\":\"Vector2i(-55, 21)\",\"source_id\":\"-1\"}","{\"alternative_tile\":\"-1\",\"atlas_coords\":\"Vector2i(-1, -1)\",\"coordinate\":\"Vector2i(-55, 22)\",\"source_id\":\"-1\"}","{\"alternative_tile\":\"-1\",\"atlas_coords\":\"Vector2i(-1, -1)\",\"coordinate\":\"Vector2i(-55, 23)\",\"source_id\":\"-1\"}","{\"alternative_tile\":\"-1\",\"atlas_coords\":\"Vector2i(-1, -1)\",\"coordinate\":\"Vector2i(-54, 16)\",\"source_id\":\"-1\"}","{\"alternative_tile\":\"-1\",\"atlas_coords\":\"Vector2i(-1, -1)\",\"coordinate\":\"Vector2i(-54, 17)\",\"source_id\":\"-1\"}","{\"alternative_tile\":\"-1\",\"atlas_coords\":\"Vector2i(-1, -1)\",\"coordinate\":\"Vector2i(-54, 18)\",\"source_id\":\"-1\"}","{\"alternative_tile\":\"-1\",\"atlas_coords\":\"Vector2i(-1, -1)\",\"coordinate\":\"Vector2i(-54, 19)\",\"source_id\":\"-1\"}","{\"alternative_tile\":\"-1\",\"atlas_coords\":\"Vector2i(-1, -1)\",\"coordinate\":\"Vector2i(-54, 20)\",\"source_id\":\"-1\"}","{\"alternative_tile\":\"-1\",\"atlas_coords\":\"Vector2i(-1, -1)\",\"coordinate\":\"Vector2i(-54, 21)\",\"source_id\":\"-1\"}","{\"alternative_tile\":\"-1\",\"atlas_coords\":\"Vector2i(-1, -1)\",\"coordinate\":\"Vector2i(-54, 22)\",\"source_id\":\"-1\"}","{\"alternative_tile\":\"-1\",\"atlas_coords\":\"Vector2i(-1, -1)\",\"coordinate\":\"Vector2i(-54, 23)\",\"source_id\":\"-1\"}","{\"alternative_tile\":\"-1\",\"atlas_coords\":\"Vector2i(-1, -1)\",\"coordinate\":\"Vector2i(-53, 16)\",\"source_id\":\"-1\"}","{\"alternative_tile\":\"-1\",\"atlas_coords\":\"Vector2i(-1, -1)\",\"coordinate\":\"Vector2i(-53, 17)\",\"source_id\":\"-1\"}","{\"alternative_tile\":\"-1\",\"atlas_coords\":\"Vector2i(-1, -1)\",\"coordinate\":\"Vector2i(-53, 18)\",\"source_id\":\"-1\"}","{\"alternative_tile\":\"-1\",\"atlas_coords\":\"Vector2i(-1, -1)\",\"coordinate\":\"Vector2i(-53, 19)\",\"source_id\":\"-1\"}","{\"alternative_tile\":\"-1\",\"atlas_coords\":\"Vector2i(-1, -1)\",\"coordinate\":\"Vector2i(-53, 20)\",\"source_id\":\"-1\"}","{\"alternative_tile\":\"-1\",\"atlas_coords\":\"Vector2i(-1, -1)\",\"coordinate\":\"Vector2i(-53, 21)\",\"source_id\":\"-1\"}","{\"alternative_tile\":\"-1\",\"atlas_coords\":\"Vector2i(-1, -1)\",\"coordinate\":\"Vector2i(-53, 22)\",\"source_id\":\"-1\"}","{\"alternative_tile\":\"-1\",\"atlas_coords\":\"Vector2i(-1, -1)\",\"coordinate\":\"Vector2i(-53, 23)\",\"source_id\":\"-1\"}","{\"alternative_tile\":\"-1\",\"atlas_coords\":\"Vector2i(-1, -1)\",\"coordinate\":\"Vector2i(-52, 16)\",\"source_id\":\"-1\"}","{\"alternative_tile\":\"-1\",\"atlas_coords\":\"Vector2i(-1, -1)\",\"coordinate\":\"Vector2i(-52, 17)\",\"source_id\":\"-1\"}","{\"alternative_tile\":\"-1\",\"atlas_coords\":\"Vector2i(-1, -1)\",\"coordinate\":\"Vector2i(-52, 18)\",\"source_id\":\"-1\"}","{\"alternative_tile\":\"-1\",\"atlas_coords\":\"Vector2i(-1, -1)\",\"coordinate\":\"Vector2i(-52, 19)\",\"source_id\":\"-1\"}","{\"alternative_tile\":\"-1\",\"atlas_coords\":\"Vector2i(-1, -1)\",\"coordinate\":\"Vector2i(-52, 20)\",\"source_id\":\"-1\"}","{\"alternative_tile\":\"-1\",\"atlas_coords\":\"Vector2i(-1, -1)\",\"coordinate\":\"Vector2i(-52, 21)\",\"source_id\":\"-1\"}","{\"alternative_tile\":\"-1\",\"atlas_coords\":\"Vector2i(-1, -1)\",\"coordinate\":\"Vector2i(-52, 22)\",\"source_id\":\"-1\"}","{\"alternative_tile\":\"-1\",\"atlas_coords\":\"Vector2i(-1, -1)\",\"coordinate\":\"Vector2i(-52, 23)\",\"source_id\":\"-1\"}","{\"alternative_tile\":\"-1\",\"atlas_coords\":\"Vector2i(-1, -1)\",\"coordinate\":\"Vector2i(-51, 16)\",\"source_id\":\"-1\"}","{\"alternative_tile\":\"-1\",\"atlas_coords\":\"Vector2i(-1, -1)\",\"coordinate\":\"Vector2i(-51, 17)\",\"source_id\":\"-1\"}","{\"alternative_tile\":\"-1\",\"atlas_coords\":\"Vector2i(-1, -1)\",\"coordinate\":\"Vector2i(-51, 18)\",\"source_id\":\"-1\"}","{\"alternative_tile\":\"-1\",\"atlas_coords\":\"Vector2i(-1, -1)\",\"coordinate\":\"Vector2i(-51, 19)\",\"source_id\":\"-1\"}","{\"alternative_tile\":\"-1\",\"atlas_coords\":\"Vector2i(-1, -1)\",\"coordinate\":\"Vector2i(-51, 20)\",\"source_id\":\"-1\"}","{\"alternative_tile\":\"-1\",\"atlas_coords\":\"Vector2i(-1, -1)\",\"coordinate\":\"Vector2i(-51, 21)\",\"source_id\":\"-1\"}","{\"alternative_tile\":\"-1\",\"atlas_coords\":\"Vector2i(-1, -1)\",\"coordinate\":\"Vector2i(-51, 22)\",\"source_id\":\"-1\"}","{\"alternative_tile\":\"-1\",\"atlas_coords\":\"Vector2i(-1, -1)\",\"coordinate\":\"Vector2i(-51, 23)\",\"source_id\":\"-1\"}","{\"alternative_tile\":\"-1\",\"atlas_coords\":\"Vector2i(-1, -1)\",\"coordinate\":\"Vector2i(-50, 16)\",\"source_id\":\"-1\"}","{\"alternative_tile\":\"-1\",\"atlas_coords\":\"Vector2i(-1, -1)\",\"coordinate\":\"Vector2i(-50, 17)\",\"source_id\":\"-1\"}","{\"alternative_tile\":\"-1\",\"atlas_coords\":\"Vector2i(-1, -1)\",\"coordinate\":\"Vector2i(-50, 18)\",\"source_id\":\"-1\"}","{\"alternative_tile\":\"-1\",\"atlas_coords\":\"Vector2i(-1, -1)\",\"coordinate\":\"Vector2i(-50, 19)\",\"source_id\":\"-1\"}","{\"alternative_tile\":\"-1\",\"atlas_coords\":\"Vector2i(-1, -1)\",\"coordinate\":\"Vector2i(-50, 20)\",\"source_id\":\"-1\"}","{\"alternative_tile\":\"1\",\"atlas_coords\":\"Vector2i(0, 0)\",\"coordinate\":\"Vector2i(-50, 21)\",\"source_id\":\"1\"}","{\"alternative_tile\":\"-1\",\"atlas_coords\":\"Vector2i(-1, -1)\",\"coordinate\":\"Vector2i(-50, 22)\",\"source_id\":\"-1\"}","{\"alternative_tile\":\"-1\",\"atlas_coords\":\"Vector2i(-1, -1)\",\"coordinate\":\"Vector2i(-50, 23)\",\"source_id\":\"-1\"}","{\"alternative_tile\":\"-1\",\"atlas_coords\":\"Vector2i(-1, -1)\",\"coordinate\":\"Vector2i(-49, 16)\",\"source_id\":\"-1\"}","{\"alternative_tile\":\"-1\",\"atlas_coords\":\"Vector2i(-1, -1)\",\"coordinate\":\"Vector2i(-49, 17)\",\"source_id\":\"-1\"}","{\"alternative_tile\":\"-1\",\"atlas_coords\":\"Vector2i(-1, -1)\",\"coordinate\":\"Vector2i(-49, 18)\",\"source_id\":\"-1\"}","{\"alternative_tile\":\"-1\",\"atlas_coords\":\"Vector2i(-1, -1)\",\"coordinate\":\"Vector2i(-49, 19)\",\"source_id\":\"-1\"}","{\"alternative_tile\":\"-1\",\"atlas_coords\":\"Vector2i(-1, -1)\",\"coordinate\":\"Vector2i(-49, 20)\",\"source_id\":\"-1\"}","{\"alternative_tile\":\"-1\",\"atlas_coords\":\"Vector2i(-1, -1)\",\"coordinate\":\"Vector2i(-49, 21)\",\"source_id\":\"-1\"}","{\"alternative_tile\":\"-1\",\"atlas_coords\":\"Vector2i(-1, -1)\",\"coordinate\":\"Vector2i(-49, 22)\",\"source_id\":\"-1\"}","{\"alternative_tile\":\"-1\",\"atlas_coords\":\"Vector2i(-1, -1)\",\"coordinate\":\"Vector2i(-49, 23)\",\"source_id\":\"-1\"}"]}